bcal/__init__.py
bcal/calculator.py
bcal/factorial.py
bcal-0.1.2.dist-info/LICENSE
bcal-0.1.2.dist-info/METADATA
bcal-0.1.2.dist-info/WHEEL
bcal-0.1.2.dist-info/top_level.txt
bcal-0.1.2.dist-info/RECORD
